NeuroSkyPy/IO.py
NeuroSkyPy/NeuroSkyPy.py
NeuroSkyPy/__init__.py
NeuroSkyPy-1.6.dist-info/LICENSE
NeuroSkyPy-1.6.dist-info/METADATA
NeuroSkyPy-1.6.dist-info/WHEEL
NeuroSkyPy-1.6.dist-info/top_level.txt
NeuroSkyPy-1.6.dist-info/RECORD
