Metadata-Version: 2.1
Name: NeuroSkyPy
Version: 1.6
Summary: Library for interfacing with Neurosky's Mindwave EEG headset
Home-page: https://github.com/Jor-G-ete/NeuroSkyPy
Author: Jorge Lopez Marcos
Author-email: jlomar2005@hotmail.com
Maintainer: Jorge Lopez Marcos
Maintainer-email: jlomar2005@hotmail.com
License: GNU General Public License v3.0
Download-URL: https://github.com/Jor-G-ete/NeuroSkyPy/archive/v1.6.tar.gz
Project-URL: Documentation, https://github.com/Jor-G-ete/NeuroSkyPy
Project-URL: Source Code, https://github.com/Jor-G-ete/NeuroSkyPy/blob/master/NeuroSkyPy/NeuroSkyPy.py
Keywords: python3.7,NeuroSky,graphics,threads
Platform: Windows
Classifier: Development Status :: 4 - Beta
Classifier: Intended Audience :: Developers
Classifier: Topic :: Software Development :: Build Tools
Classifier: License :: OSI Approved :: GNU General Public License v3 or later (GPLv3+)
Classifier: Programming Language :: Python :: 3
Classifier: Programming Language :: Python :: 3.7
Classifier: Natural Language :: English
Classifier: Natural Language :: Spanish
Classifier: Operating System :: Microsoft :: Windows :: Windows 10
Classifier: Topic :: Scientific/Engineering :: Medical Science Apps.
Requires-Python: >=3.7
Requires-Dist: numpy
Requires-Dist: scikit-learn
Requires-Dist: matplotlib
Requires-Dist: pyserial
Requires-Dist: pyyaml
